{"nodes": [{"id": "05_stripe_double_send_test", "label": "05-stripe-double-send.test.ts", "file_type": "code", "source_file": "tests\\sms-regression\\05-stripe-double-send.test.ts", "source_location": "L1"}], "edges": [{"source": "05_stripe_double_send_test", "target": "vitest", "relation": "imports_from", "confidence": "EXTRACTED", "source_file": "tests\\sms-regression\\05-stripe-double-send.test.ts", "source_location": "L12", "weight": 1.0}, {"source": "05_stripe_double_send_test", "target": "modules", "relation": "imports_from", "confidence": "EXTRACTED", "source_file": "tests\\sms-regression\\05-stripe-double-send.test.ts", "source_location": "L13", "weight": 1.0}, {"source": "05_stripe_double_send_test", "target": "cedar_rapids", "relation": "imports_from", "confidence": "EXTRACTED", "source_file": "tests\\sms-regression\\05-stripe-double-send.test.ts", "source_location": "L14", "weight": 1.0}, {"source": "05_stripe_double_send_test", "target": "payloads", "relation": "imports_from", "confidence": "EXTRACTED", "source_file": "tests\\sms-regression\\05-stripe-double-send.test.ts", "source_location": "L15", "weight": 1.0}]}