{"nodes": [{"id": "09_telegram_accept_test", "label": "09-telegram-accept.test.ts", "file_type": "code", "source_file": "tests\\cedar-rapids\\09-telegram-accept.test.ts", "source_location": "L1"}], "edges": [{"source": "09_telegram_accept_test", "target": "vitest", "relation": "imports_from", "confidence": "EXTRACTED", "source_file": "tests\\cedar-rapids\\09-telegram-accept.test.ts", "source_location": "L5", "weight": 1.0}, {"source": "09_telegram_accept_test", "target": "modules", "relation": "imports_from", "confidence": "EXTRACTED", "source_file": "tests\\cedar-rapids\\09-telegram-accept.test.ts", "source_location": "L6", "weight": 1.0}, {"source": "09_telegram_accept_test", "target": "cedar_rapids", "relation": "imports_from", "confidence": "EXTRACTED", "source_file": "tests\\cedar-rapids\\09-telegram-accept.test.ts", "source_location": "L16", "weight": 1.0}]}